json_formatter_tool/__init__.py
json_formatter_tool/formatter.py
json_formatter_tool-0.1.0.dist-info/METADATA
json_formatter_tool-0.1.0.dist-info/WHEEL
json_formatter_tool-0.1.0.dist-info/top_level.txt
json_formatter_tool-0.1.0.dist-info/RECORD
